fabik/__init__.py
fabik/__main__.py
fabik/cli.py
fabik/cmd.py
fabik/conf.py
fabik/error.py
fabik/http.py
fabik/log.py
fabik/tpl.py
fabik/deploy/__init__.py
fabik/deploy/gunicorn.py
fabik/deploy/tmux.py
fabik/deploy/uwsgi.py
fabik/util/__init__.py
fabik/util/date.py
fabik/util/encrypt.py
fabik/util/func.py
fabik/util/gen.py
fabik/util/jinja_filter.py
fabik-25.7.1.dist-info/entry_points.txt
fabik-25.7.1.dist-info/licenses/LICENSE
fabik-25.7.1.dist-info/WHEEL
fabik-25.7.1.dist-info/METADATA
fabik-25.7.1.dist-info/RECORD
