Metadata-Version: 2.4
Name: fabik
Version: 25.7.1
Summary: fabik is a library for Python command line application.
Keywords: development,zrong,typer,cli,tool
Author-email: zrong <zrongzrong@gmail.com>
Requires-Python: >=3.13
Classifier: Development Status :: 4 - Beta
Classifier: Intended Audience :: Developers
Classifier: Environment :: Console
Classifier: Environment :: Web Environment
Classifier: Topic :: Internet :: WWW/HTTP :: Site Management
Classifier: Topic :: Utilities
Classifier: Topic :: Software Development :: Libraries :: Application Frameworks
Classifier: License :: OSI Approved :: MIT License
Classifier: Operating System :: POSIX :: Linux
Classifier: Programming Language :: Python :: 3.13
License-File: LICENSE
Requires-Dist: click>=8.2.1
Requires-Dist: cryptography>=45.0.5
Requires-Dist: fabric>=3.2.2
Requires-Dist: httpx>=0.28.1
Requires-Dist: jinja2>=3.1.6
Requires-Dist: tomli-w>=1.2.0
Requires-Dist: typer-slim[standard]>=0.16.0
Project-URL: Documentation, https://fabik.rtfd.io/
Project-URL: Home, https://github.com/zrong/fabik
Project-URL: Repository, https://github.com/zrong/fabik
